qlu_api_call_util/__init__.py
qlu_api_call_util/api_call.py
qlu_api_call_util/utility.py
qlu_api_call_util-0.0.12.dist-info/LICENSE
qlu_api_call_util-0.0.12.dist-info/METADATA
qlu_api_call_util-0.0.12.dist-info/WHEEL
qlu_api_call_util-0.0.12.dist-info/top_level.txt
qlu_api_call_util-0.0.12.dist-info/RECORD
