Metadata-Version: 2.1
Name: qlu-api-call-util
Version: 0.0.12
Summary: A small example package
Author-email: Aasharib <aasharib01@gmail.com>
Project-URL: Homepage, https://github.com/aasharib/qlu_api_call_util.git
Project-URL: Bug Tracker, https://github.com/aasharib/qlu_api_call_util/issues
Classifier: Programming Language :: Python :: 3
Classifier: License :: OSI Approved :: MIT License
Classifier: Operating System :: OS Independent
Requires-Python: >=3.7
License-File: LICENSE
Requires-Dist: aiohttp
Requires-Dist: asyncio
